LICENSE.txt
README.txt
asiconsole.py
setup.cfg
setup.py
asiconsole.egg-info/PKG-INFO
asiconsole.egg-info/SOURCES.txt
asiconsole.egg-info/dependency_links.txt
asiconsole.egg-info/entry_points.txt
asiconsole.egg-info/requires.txt
asiconsole.egg-info/top_level.txt
asiconsole.egg-info/zip-safe
docs/HISTORY.txt