Metadata-Version: 1.0
Name: asiconsole
Version: 1.0.2
Summary: Python ASI console for interactive testing and debugging
Home-page: http://asibsync.sourceforge.net
Author: Eemeli Kantola
Author-email: eemeli.kantola@iki.fi
License: BSD
Keywords: ASI REST OtaSizzle console
Platform: UNKNOWN
Classifier: Intended Audience :: Developers
Classifier: Development Status :: 4 - Beta
Classifier: Environment :: Console
Classifier: Programming Language :: Python :: 2.6
Classifier: Topic :: Internet
